<?xml version="1.0" ?>
<getthis reportall="">
    <output compression="fast"/>
    <location>%SystemDrive%\</location>
    <sample name="WindowsGroupPolicyScripts">
        <ntfs_find path_match="Windows\System32\GroupPolicy\User\Scripts\psscripts.ini"/>
    </sample>
    <sample name="WindowsGroupPolicyScripts">
        <ntfs_find path_match="Windows\System32\GroupPolicy\User\Scripts\scripts.ini"/>
    </sample>
    <sample name="WindowsGroupPolicyScripts">
        <ntfs_find path_match="Windows\System32\GroupPolicy\User\Scripts\Logoff\*"/>
    </sample>
    <sample name="WindowsGroupPolicyScripts">
        <ntfs_find path_match="Windows\System32\GroupPolicy\User\Scripts\Logon\*"/>
    </sample>
    <sample name="WindowsGroupPolicyScripts">
        <ntfs_find path_match="Windows\System32\GroupPolicy\Machine\Scripts\psscripts.ini"/>
    </sample>
    <sample name="WindowsGroupPolicyScripts">
        <ntfs_find path_match="Windows\System32\GroupPolicy\Machine\Scripts\scripts.ini"/>
    </sample>
    <sample name="WindowsGroupPolicyScripts">
        <ntfs_find path_match="Windows\System32\GroupPolicy\Machine\Scripts\Shutdown\*"/>
    </sample>
    <sample name="WindowsGroupPolicyScripts">
        <ntfs_find path_match="Windows\System32\GroupPolicy\Machine\Scripts\Startup\*"/>
    </sample>
</getthis>
